setup.py
fedmsg_meta_debian/__init__.py
fedmsg_meta_debian/debexpo.py
fedmsg_meta_debian/debmessenger.py
fedmsg_meta_debian/utils.py
fedmsg_meta_debian.egg-info/PKG-INFO
fedmsg_meta_debian.egg-info/SOURCES.txt
fedmsg_meta_debian.egg-info/dependency_links.txt
fedmsg_meta_debian.egg-info/entry_points.txt
fedmsg_meta_debian.egg-info/not-zip-safe
fedmsg_meta_debian.egg-info/requires.txt
fedmsg_meta_debian.egg-info/top_level.txt