Metadata-Version: 1.0
Name: fedmsg-meta-debian
Version: 0.1
Summary: fedmsg metadata providers for Debian deployment
Home-page: http://anonscm.debian.org/gitweb/?p=users/laarmen-guest/fedmsg_meta_debian.git
Author: Simon Chopin
Author-email: chopin.simon@gmail.com
License: Expat
Platform: UNKNOWN
